<InterfaceSummary>
<RtlPorts>
<name>s_axi_ar_araddr</name>
<CType>
<TypeName>void</TypeName>
<TypeWidth>8</TypeWidth>
<PhysicalWidth>64</PhysicalWidth>
</CType>
<CFractionWidth>0</CFractionWidth>
<InvalidType>0</InvalidType>
</RtlPorts>
<RtlPorts>
<name>s_axi_ar_arready</name>
<CType>
<TypeName>void</TypeName>
<TypeWidth>8</TypeWidth>
<PhysicalWidth>1</PhysicalWidth>
</CType>
<CFractionWidth>0</CFractionWidth>
<InvalidType>0</InvalidType>
</RtlPorts>
<RtlPorts>
<name>s_axi_ar_arvalid</name>
<CType>
<TypeName>void</TypeName>
<TypeWidth>8</TypeWidth>
<PhysicalWidth>1</PhysicalWidth>
</CType>
<CFractionWidth>0</CFractionWidth>
<InvalidType>0</InvalidType>
</RtlPorts>
<RtlPorts>
<name>s_axi_aw_awaddr</name>
<CType>
<TypeName>void</TypeName>
<TypeWidth>8</TypeWidth>
<PhysicalWidth>64</PhysicalWidth>
</CType>
<CFractionWidth>0</CFractionWidth>
<InvalidType>0</InvalidType>
</RtlPorts>
<RtlPorts>
<name>s_axi_aw_awready</name>
<CType>
<TypeName>void</TypeName>
<TypeWidth>8</TypeWidth>
<PhysicalWidth>1</PhysicalWidth>
</CType>
<CFractionWidth>0</CFractionWidth>
<InvalidType>0</InvalidType>
</RtlPorts>
<RtlPorts>
<name>s_axi_aw_awvalid</name>
<CType>
<TypeName>void</TypeName>
<TypeWidth>8</TypeWidth>
<PhysicalWidth>1</PhysicalWidth>
</CType>
<CFractionWidth>0</CFractionWidth>
<InvalidType>0</InvalidType>
</RtlPorts>
<RtlPorts>
<name>s_axi_b_bresp</name>
<CType>
<TypeName>void</TypeName>
<TypeWidth>8</TypeWidth>
<PhysicalWidth>2</PhysicalWidth>
</CType>
<CFractionWidth>0</CFractionWidth>
<InvalidType>0</InvalidType>
</RtlPorts>
<RtlPorts>
<name>s_axi_b_bready</name>
<CType>
<TypeName>void</TypeName>
<TypeWidth>8</TypeWidth>
<PhysicalWidth>1</PhysicalWidth>
</CType>
<CFractionWidth>0</CFractionWidth>
<InvalidType>0</InvalidType>
</RtlPorts>
<RtlPorts>
<name>s_axi_b_bvalid</name>
<CType>
<TypeName>void</TypeName>
<TypeWidth>8</TypeWidth>
<PhysicalWidth>1</PhysicalWidth>
</CType>
<CFractionWidth>0</CFractionWidth>
<InvalidType>0</InvalidType>
</RtlPorts>
<RtlPorts>
<name>s_axi_r_rdata</name>
<CType>
<TypeName>void</TypeName>
<TypeWidth>8</TypeWidth>
<PhysicalWidth>64</PhysicalWidth>
</CType>
<CFractionWidth>0</CFractionWidth>
<InvalidType>0</InvalidType>
</RtlPorts>
<RtlPorts>
<name>s_axi_r_rresp</name>
<CType>
<TypeName>void</TypeName>
<TypeWidth>8</TypeWidth>
<PhysicalWidth>2</PhysicalWidth>
</CType>
<CFractionWidth>0</CFractionWidth>
<InvalidType>0</InvalidType>
</RtlPorts>
<RtlPorts>
<name>s_axi_r_rready</name>
<CType>
<TypeName>void</TypeName>
<TypeWidth>8</TypeWidth>
<PhysicalWidth>1</PhysicalWidth>
</CType>
<CFractionWidth>0</CFractionWidth>
<InvalidType>0</InvalidType>
</RtlPorts>
<RtlPorts>
<name>s_axi_r_rvalid</name>
<CType>
<TypeName>void</TypeName>
<TypeWidth>8</TypeWidth>
<PhysicalWidth>1</PhysicalWidth>
</CType>
<CFractionWidth>0</CFractionWidth>
<InvalidType>0</InvalidType>
</RtlPorts>
<RtlPorts>
<name>s_axi_w_wdata</name>
<CType>
<TypeName>void</TypeName>
<TypeWidth>8</TypeWidth>
<PhysicalWidth>64</PhysicalWidth>
</CType>
<CFractionWidth>0</CFractionWidth>
<InvalidType>0</InvalidType>
</RtlPorts>
<RtlPorts>
<name>s_axi_w_wstrb</name>
<CType>
<TypeName>void</TypeName>
<TypeWidth>8</TypeWidth>
<PhysicalWidth>8</PhysicalWidth>
</CType>
<CFractionWidth>0</CFractionWidth>
<InvalidType>0</InvalidType>
</RtlPorts>
<RtlPorts>
<name>s_axi_w_wready</name>
<CType>
<TypeName>void</TypeName>
<TypeWidth>8</TypeWidth>
<PhysicalWidth>1</PhysicalWidth>
</CType>
<CFractionWidth>0</CFractionWidth>
<InvalidType>0</InvalidType>
</RtlPorts>
<RtlPorts>
<name>s_axi_w_wvalid</name>
<CType>
<TypeName>void</TypeName>
<TypeWidth>8</TypeWidth>
<PhysicalWidth>1</PhysicalWidth>
</CType>
<CFractionWidth>0</CFractionWidth>
<InvalidType>0</InvalidType>
</RtlPorts>
</InterfaceSummary>

